sopel_imdb/__init__.py
sopel_imdb/imdb.py
sopel_imdb-1.3.0.dist-info/licenses/LICENSE
sopel_imdb-1.3.0.dist-info/METADATA
sopel_imdb-1.3.0.dist-info/WHEEL
sopel_imdb-1.3.0.dist-info/entry_points.txt
sopel_imdb-1.3.0.dist-info/top_level.txt
sopel_imdb-1.3.0.dist-info/RECORD
