Metadata-Version: 2.4
Name: sopel-imdb
Version: 1.3.0
Summary: A re-implementation of the imdb plugin for Sopel
Author: Rusty Bower
Maintainer: Rusty Bower
License: MIT
Project-URL: Homepage, http://github.com/rustybower/sopel-imdb
Project-URL: Bug Tracker, http://github.com/rustybower/sopel-imdb/issues
Keywords: sopel,plugin,imdb,cinema,movie,bot,irc
Platform: Linux x86, x86-64
Classifier: Development Status :: 5 - Production/Stable
Classifier: Intended Audience :: Developers
Classifier: Intended Audience :: System Administrators
Classifier: Operating System :: POSIX :: Linux
Classifier: Programming Language :: Python :: 3.8
Classifier: Programming Language :: Python :: 3.9
Classifier: Programming Language :: Python :: 3.10
Classifier: Programming Language :: Python :: 3.11
Classifier: Programming Language :: Python :: 3.12
Classifier: Topic :: Communications :: Chat :: Internet Relay Chat
Requires-Python: <4,>=3.8
License-File: LICENSE
Requires-Dist: requests
Requires-Dist: sopel>=8
Dynamic: license-file
